net2cell/__init__.py
net2cell/settings.py
net2cell/io/__init__.py
net2cell/io/load_from_csv.py
net2cell/io/output_mrnet.py
net2cell/io/util_io.py
net2cell/io/writefile.py
net2cell/movement/__init__.py
net2cell/movement/autoconintd.py
net2cell/movement/autoconm.py
net2cell/movement/generate_movements.py
net2cell/movement/util_mvmt.py
net2cell/multiresolution/__init__.py
net2cell/multiresolution/build_mrnet.py
net2cell/multiresolution/netgen.py
net2cell/networkclass/__init__.py
net2cell/networkclass/basenet.py
net2cell/networkclass/macronet.py
net2cell/networkclass/mesonet.py
net2cell/networkclass/micronet.py
net2cell/osmnet/__init__.py
net2cell/osmnet/build_net.py
net2cell/osmnet/check_args.py
net2cell/osmnet/combine_links.py
net2cell/osmnet/complex_intersection.py
net2cell/osmnet/enrich_net_info.py
net2cell/osmnet/osmclasses.py
net2cell/osmnet/pois.py
net2cell/osmnet/read_from_osm.py
net2cell/osmnet/wayfilters.py
net2cell/utils/__init__.py
net2cell/utils/util.py
net2cell/utils/util_coord.py
net2cell/utils/util_geo.py
net2cell-0.1.2.dist-info/licenses/LICENSE
net2cell-0.1.2.dist-info/METADATA
net2cell-0.1.2.dist-info/WHEEL
net2cell-0.1.2.dist-info/top_level.txt
net2cell-0.1.2.dist-info/RECORD
