Metadata-Version: 2.4
Name: net2cell
Version: 0.1.2
Summary: A multi-resolution network builder for GMNS networks
Author: Jiawei Lu, Xuesong Zhou
Author-email: Yajun Liu <yajunliu@asu.edu>
License-Expression: GPL-3.0-or-later
Keywords: multi-resolution,network,GMNS,transportation,GIS,OSM,meso,micro
Classifier: Development Status :: 3 - Alpha
Classifier: Intended Audience :: Science/Research
Classifier: Intended Audience :: Developers
Classifier: Programming Language :: Python :: 3
Classifier: Topic :: Scientific/Engineering :: GIS
Requires-Python: >=3.8
License-File: LICENSE
Requires-Dist: numpy>=1.20.0
Requires-Dist: pandas>=1.3.0
Requires-Dist: shapely>=2.0.0
Requires-Dist: geopandas>=0.10.0
Requires-Dist: networkx>=2.6.0
Requires-Dist: osmium>=3.5.0
Provides-Extra: dev
Requires-Dist: pytest>=7.0.0; extra == "dev"
Requires-Dist: pytest-cov>=3.0.0; extra == "dev"
Requires-Dist: black>=22.0.0; extra == "dev"
Requires-Dist: flake8>=4.0.0; extra == "dev"
Dynamic: license-file
